Metadata-Version: 2.1
Name: auth-package
Version: 1.0
Summary: Auth package for authentication with microservices
Home-page: https://www.ramzamani.com/
Download-URL: https://github.com/zamaniramin549/auth_project_package/archive/refs/tags/1.0.tar.gz
Author: Ramin Zamanighiri
Author-email: zamaniramin549@gmail.com
License: mit
Keywords: microservices,Auth package,API
Classifier: Development Status :: 4 - Beta
Classifier: Intended Audience :: Developers
Classifier: Topic :: Software Development :: Build Tools
Classifier: License :: OSI Approved :: MIT License
Classifier: Programming Language :: Python :: 3
Classifier: Programming Language :: Python :: 3.4
Classifier: Programming Language :: Python :: 3.5
Classifier: Programming Language :: Python :: 3.6
Classifier: Programming Language :: Python :: 3.7
Classifier: Programming Language :: Python :: 3.8
Classifier: Programming Language :: Python :: 3.9
Classifier: Programming Language :: Python :: 3.10
License-File: LICENSE.txt
